[{"hospede":"07-1214455","dataEntrada":"2018-11-01T07:28:17Z","dataSaida":"2018-10-11T04:54:27Z","adicionalEstacionamento":false},
{"hospede":"22-5958937","dataEntrada":"2019-07-19T08:51:34Z","dataSaida":"2019-07-04T07:42:41Z","adicionalEstacionamento":true},
{"hospede":"40-1756499","dataEntrada":"2019-08-23T10:24:41Z","dataSaida":"2019-02-11T06:08:23Z","adicionalEstacionamento":false},
{"hospede":"11-8879843","dataEntrada":"2019-02-22T16:28:49Z","dataSaida":"2019-07-30T08:04:33Z","adicionalEstacionamento":true},
{"hospede":"21-1177580","dataEntrada":"2018-11-28T13:30:47Z","dataSaida":"2019-02-05T10:56:01Z","adicionalEstacionamento":true},
{"hospede":"41-0687794","dataEntrada":"2019-06-20T23:17:01Z","dataSaida":"2018-12-04T22:36:11Z","adicionalEstacionamento":true},
{"hospede":"39-7854733","dataEntrada":"2019-08-17T20:16:15Z","dataSaida":"2019-03-16T10:28:36Z","adicionalEstacionamento":true},
{"hospede":"74-9858430","dataEntrada":"2019-08-10T07:35:14Z","dataSaida":"2018-12-26T20:28:11Z","adicionalEstacionamento":false},
{"hospede":"60-6473838","dataEntrada":"2019-04-22T04:15:23Z","dataSaida":"2019-09-28T11:32:24Z","adicionalEstacionamento":true},
{"hospede":"09-2302231","dataEntrada":"2018-12-21T17:37:04Z","dataSaida":"2019-04-29T06:47:02Z","adicionalEstacionamento":true},
{"hospede":"71-8980118","dataEntrada":"2018-10-09T13:43:28Z","dataSaida":"2019-06-11T04:16:20Z","adicionalEstacionamento":true},
{"hospede":"57-5124337","dataEntrada":"2019-06-18T06:17:04Z","dataSaida":"2018-10-18T20:53:32Z","adicionalEstacionamento":false},
{"hospede":"00-7549672","dataEntrada":"2019-02-03T17:30:57Z","dataSaida":"2019-02-07T09:24:26Z","adicionalEstacionamento":false},
{"hospede":"68-0253521","dataEntrada":"2018-10-27T09:33:46Z","dataSaida":"2019-02-06T21:06:08Z","adicionalEstacionamento":true},
{"hospede":"24-2204940","dataEntrada":"2018-11-20T19:38:18Z","dataSaida":"2019-07-09T15:38:20Z","adicionalEstacionamento":true},
{"hospede":"41-8746291","dataEntrada":"2019-08-31T08:49:59Z","dataSaida":"2019-01-17T09:12:23Z","adicionalEstacionamento":false},
{"hospede":"42-9798440","dataEntrada":"2019-04-26T05:19:48Z","dataSaida":"2019-07-03T06:40:33Z","adicionalEstacionamento":true},
{"hospede":"55-0213865","dataEntrada":"2019-09-10T15:09:12Z","dataSaida":"2019-05-11T00:42:04Z","adicionalEstacionamento":true},
{"hospede":"42-9997899","dataEntrada":"2019-02-05T10:02:56Z","dataSaida":"2018-11-11T04:36:00Z","adicionalEstacionamento":false},
{"hospede":"26-2389057","dataEntrada":"2018-11-02T14:25:34Z","dataSaida":"2019-02-05T22:13:07Z","adicionalEstacionamento":false}]